{
    "article3": [
        {
            "id": 9,
            "title": "FUERTE GOLPE PARA EL JUGADOR RAMIRO FUNES MORI",
            "description": "",
            "img": "RamiroFunesMori.png"
        },
        {
            "id": 10,
            "title": "SUSANA GIMENEZ SE POSTERGO POR PROBLEMA DE SALUD",
            "description": "",
            "img": "susana.png"
        },
        {
            "id": 11,
            "title": "EL CLUB DEPORTIVO MAIPU NO LLEGO AL ASCENSO",
            "description": "",
            "img": "cancha.png"
        },
        {
            "id": 12,
            "title": "ALBERTO FERNADEZ COBRARA UNA MILLONARIA JUBILACIÓN",
            "description": "",
            "img": "albertito.png"
        }
    ]
}